azure/functions/__init__.py
azure/functions/_abc.py
azure/functions/_blob.py
azure/functions/_cosmosdb.py
azure/functions/_durable_functions.py
azure/functions/_eventgrid.py
azure/functions/_eventhub.py
azure/functions/_http.py
azure/functions/_http_asgi.py
azure/functions/_http_wsgi.py
azure/functions/_kafka.py
azure/functions/_mysql.py
azure/functions/_queue.py
azure/functions/_servicebus.py
azure/functions/_sql.py
azure/functions/_timer.py
azure/functions/_utils.py
azure/functions/meta.py
azure/functions/py.typed
azure/functions/_thirdparty/__init__.py
azure/functions/_thirdparty/typing_inspect.py
azure/functions/decorators/__init__.py
azure/functions/decorators/blob.py
azure/functions/decorators/constants.py
azure/functions/decorators/core.py
azure/functions/decorators/cosmosdb.py
azure/functions/decorators/dapr.py
azure/functions/decorators/eventgrid.py
azure/functions/decorators/eventhub.py
azure/functions/decorators/function_app.py
azure/functions/decorators/function_name.py
azure/functions/decorators/generic.py
azure/functions/decorators/http.py
azure/functions/decorators/kafka.py
azure/functions/decorators/openai.py
azure/functions/decorators/queue.py
azure/functions/decorators/retry_policy.py
azure/functions/decorators/servicebus.py
azure/functions/decorators/sql.py
azure/functions/decorators/table.py
azure/functions/decorators/timer.py
azure/functions/decorators/utils.py
azure/functions/decorators/warmup.py
tests/decorators/test_blob.py
tests/decorators/test_core.py
tests/decorators/test_cosmosdb.py
tests/decorators/test_dapr.py
tests/decorators/test_decorators.py
tests/decorators/test_eventgrid.py
tests/decorators/test_eventhub.py
tests/decorators/test_function_app.py
tests/decorators/test_function_name.py
tests/decorators/test_generic.py
tests/decorators/test_http.py
tests/decorators/test_kafka.py
tests/decorators/test_openai.py
tests/decorators/test_queue.py
tests/decorators/test_retry_policy.py
tests/decorators/test_servicebus.py
vtest_sdk-1.0.0a4.dist-info/LICENSE
vtest_sdk-1.0.0a4.dist-info/METADATA
vtest_sdk-1.0.0a4.dist-info/WHEEL
vtest_sdk-1.0.0a4.dist-info/top_level.txt
vtest_sdk-1.0.0a4.dist-info/RECORD
