Metadata-Version: 2.2
Name: vtest-sdk
Version: 1.0.0a4
License-File: LICENSE
Requires-Dist: werkzeug~=3.1.3; python_version >= "3.9"
Requires-Dist: werkzeug~=3.0.6; python_version == "3.8"
Requires-Dist: werkzeug; python_version < "3.8"
Provides-Extra: dev
Requires-Dist: pytest; extra == "dev"
Requires-Dist: pytest-cov; extra == "dev"
Requires-Dist: coverage; extra == "dev"
Requires-Dist: pytest-instafail; extra == "dev"
Requires-Dist: pre-commit; extra == "dev"
Requires-Dist: azure-functions-durable; extra == "dev"
Requires-Dist: flake8~=4.0.1; python_version < "3.11" and extra == "dev"
Requires-Dist: flake8~=7.1.1; python_version >= "3.11" and extra == "dev"
